{
    "Quantum Chemistry as a Benchmark for Near-Term Quantum Computers": [
        "USA"
    ],
    "From Ans\u00e4tze to Z-gates: a NASA View of Quantum Computing": [],
    "Dynamical mean field theory algorithm and experiment on quantum computers": [],
    "Error detection on quantum computers improves accuracy of chemical calculations": [
        "USA"
    ],
    "Separation and approximate separation of multipartite quantum gates": [],
    "Demonstration of Minisuperspace Quantum Cosmology Using Quantum Computational Algorithms on IBM Quantum Computer": [
        "India"
    ],
    "A Lightweight McEliece Cryptosystem Co-processor Design": [
        "United States"
    ],
    "Semiconductor Quantum Computation": [
        "China"
    ],
    "Crossing a topological phase transition with a quantum computer": [
        "Germany",
        "United Kingdom"
    ],
    "Quantum Probability: a reliable tool for an agent or a reliable source of reality?": [
        "Argentina",
        "Belgium",
        "Italy"
    ],
    "A Scalable Quantum Computing Platform Using Symmetric-Top Molecules": [
        "USA"
    ],
    "Characterizing large-scale quantum computers via cycle benchmarking": [
        "Austria"
    ],
    "State Stabilization for Gate-Model Quantum Computers": [],
    "Minimizing polynomial functions on quantum computers": [
        "United States"
    ],
    "OpticalGAN : Generative Adversarial Networks for Continuous Variable Quantum Computation": [],
    "Training Optimization for Gate-Model Quantum Neural Networks": [],
    "Fine-grained quantum supremacy based on Orthogonal Vectors, 3-SUM and All-Pairs Shortest Paths": [
        "Japan"
    ],
    "Nash embedding: a road map to realizing quantum hardware": [
        "USA",
        "UAE"
    ],
    "Quantum Computing as a High School Module": [],
    "Are all Gaussian states also cluster states? Essential diagnostic tools for continuous-variable one-way quantum computing": [
        "USA"
    ],
    "Digital-analog quantum algorithm for the quantum Fourier transform": [
        "Spain"
    ],
    "Quantum Computation of the Massive Thirring Model": [
        "USA"
    ],
    "Holistic type extension for classical propositional logic in quantum computation": [
        "Italy"
    ],
    "Symmetry Configuration Mapping for Representing Quantum Systems on Quantum Computers": [
        "USA"
    ],
    "Challenges and Opportunities of Near-Term Quantum Computing Systems": [],
    "On the qubit routing problem": [
        "UK",
        "France"
    ],
    "Quantum Bridge Analytics II: Network Optimization and Combinatorial Chaining for Asset Exchange": [],
    "Reliable quantum circuits have defects": [],
    "Machine learning methods in quantum computing theory": [
        "Russia"
    ],
    "A Contextual $\u03c8$-Epistemic Model of the $n$-Qubit Stabilizer Formalism": [
        "Canada"
    ],
    "Cross-verification of independent quantum devices": [
        "Austria"
    ],
    "Faster quantum computation with permutations and resonant couplings": [
        "United Kingdom",
        "Singapore"
    ],
    "Blind quantum computation with a heralded single photon source": [
        "Japan"
    ],
    "QCOR: A Language Extension Specification for the Heterogeneous Quantum-Classical Model of Computation": [
        "United States"
    ],
    "Every Action in Every Code is Fault Tolerant: Fault Tolerance Quantum Computation in Quotient Algebra Partition": [
        "Taiwan"
    ],
    "The impact of quantum computing on real-world security: A 5G case study": [
        "United Kingdom"
    ],
    "Universal Quantum Computation by a Single Photon": [
        "Austria"
    ],
    "Quantum circuits for maximally entangled states": [
        "Spain",
        "Netherlands"
    ],
    "Quantum computing for accelerating cross-correlations intensive applications in signal processing": [
        "The Netherlands"
    ],
    "An Improved Implementation Approach for Quantum Phase Estimation on Quantum Computers": [
        "USA"
    ],
    "Photonic quantum information processing: a concise review": [
        "Australia"
    ],
    "Quantum computing, Seifert surfaces and singular fibers": [],
    "Efficient Arbitrary Simultaneously Entangling Gates on a trapped-ion quantum computer": [
        "USA"
    ],
    "A hybrid algorithm framework for small quantum computers with application to finding Hamiltonian cycles": [
        "Germany",
        "Netherlands"
    ],
    "Optimized Compilation of Aggregated Instructions for Realistic Quantum Computers": [
        "United States"
    ],
    "Calculation of $\u03c0$ on the IBM quantum computer and the accuracy of one-qubit operations": [
        "Russia"
    ],
    "Local certification of programmable quantum devices of arbitrary high dimensionality": [
        "Singapore",
        "Spain"
    ],
    "Knot theory and quantum computing": [],
    "Towards Solving the Navier-Stokes Equation on Quantum Computers": [
        "United States"
    ],
    "Towards Pricing Financial Derivatives with an IBM Quantum Computer": [
        "Spain"
    ],
    "Toward convergence of effective field theory simulations on digital quantum computers": [
        "USA"
    ],
    "Benchmarking an 11-qubit quantum computer": [],
    "Quantum Computer Systems for Scientific Discovery": [],
    "A practicable guide to the quantum computation architectures": [
        "China",
        "UAE"
    ],
    "Zeta-regularized vacuum expectation values from quantum computing simulations": [
        "Germany",
        "United Kingdom"
    ],
    "Computational Chemistry on Quantum Computers: Ground state estimation": [
        "Greece"
    ],
    "Multiple multi-control unitary operations: implementation and applications": [
        "China"
    ],
    "Continuous-variable quantum computing in the quantum optical frequency comb": [
        "USA"
    ],
    "Evidence of the entanglement constraint on wave-particle duality using the IBM Q quantum computer": [
        "Switzerland"
    ],
    "Quantum computer with cold ions in the Aubry pinned phase": [
        "France"
    ],
    "Practical Quantum Computation of Chemical and Nuclear Energy Levels Using Quantum Imaginary Time Evolution and Lanczos Algorithms": [
        "USA"
    ],
    "Making Quantum Computing Open: Lessons from Open-Source Projects": [
        "USA"
    ],
    "Fine-grained quantum computational supremacy": [
        "Japan"
    ],
    "Quantum Computing with sine-Gordon Qubits": [
        "Canada"
    ],
    "Homomorphic encryption of linear optics quantum computation on almost arbitrary states of light with asymptotically perfect security": [
        "United Kingdom"
    ],
    "Approaching graph problems with continuous variable quantum computing": [],
    "Quantum Coin Method for Numerical Integration": [
        "Japan"
    ],
    "Performance and error modeling of Deutsch's algorithm in IBM Q": [
        "Uruguay"
    ],
    "Universal Variational Quantum Computation": [
        "Russia"
    ],
    "Quantum Computing: An Overview Across the System Stack": [
        "United States"
    ],
    "Flying Unicorn: Developing a Game for a Quantum Computer": [],
    "Driven-dissipative quantum mechanics on a lattice: Simulating a fermionic reservoir on a quantum computer": [
        "USA"
    ],
    "Quantum-Computing Architecture based on Large-Scale Multi-Dimensional Continuous-Variable Cluster States in a Scalable Photonic Platform": [
        "USA"
    ],
    "A HoTT Quantum Equational Theory (Extended Version)": [
        "USA"
    ],
    "Quantum computation of magnon spectra": [
        "USA"
    ],
    "Nonadiabatic holonomic multiqubit controlled gates": [
        "China"
    ],
    "Quantum Computation with Machine-Learning-Controlled Quantum Stuff": [
        "Canada"
    ],
    "Scalable nonadiabatic holonomic quantum computation on a superconducting qubit lattice": [
        "China"
    ],
    "Remote blind state preparation with weak coherent pulses in the field": [
        "China"
    ],
    "Sumcheck-based delegation of quantum computing to rational server": [
        "Japan"
    ],
    "Simulating Cognition with Quantum Computers": [
        "USA"
    ],
    "Three-qubit exact Grover within the blind oracular quantum computation scheme": [],
    "Perspective: Toward large-scale fault-tolerant universal photonic quantum computing": [
        "Japan"
    ],
    "Local Dimension Invariant Qudit Stabilizer Codes": [
        "Canada"
    ],
    "Experimental Evidence about \"A factorisation algorithm in adiabatic quantum computation\" by T. D. Kieu": [],
    "Time-Domain Multiplexed 2-Dimensional Cluster State: Universal Quantum Computing Platform": [
        "Japan"
    ],
    "Implications of Quantum Computing for Artificial Intelligence alignment research": [],
    "Quantum Computer Control using Novel, Hybrid Semiconductor-Superconductor Electronics": [
        "United States"
    ],
    "A Quantum Computational Approach to Correspondence Problems on Point Sets": [
        "Germany"
    ],
    "Scalable quantum computer with superconducting circuits in the ultrastrong coupling regime": [
        "Japan",
        "Italy"
    ],
    "Cost-Reduced All-Gaussian Universality with the Gottesman-Kitaev-Preskill Code: Resource-Theoretic Approach to Cost Analysis": [
        "Japan"
    ],
    "Foundational Patterns for Efficient Quantum Computing": [],
    "Demonstration of teleportation-based error correction in the IBM quantum computer": [
        "India"
    ],
    "Convolution filter embedded quantum gate autoencoder": [
        "Japan"
    ],
    "Robust universal Hamiltonian quantum computing using two-body interactions": [
        "USA"
    ],
    "Applications of Quantum Annealing in Statistics": [
        "United States"
    ],
    "Quantum Computing at the Frontiers of Biological Sciences": [],
    "A Full Quantum Eigensolver for Quantum Chemistry Simulations": [
        "China"
    ],
    "When will we have a quantum computer?": [
        "France"
    ],
    "Compiling basic linear algebra subroutines for quantum computers": [
        "Singapore"
    ],
    "The Implementation of Quantum Computing Operations with Phase Modulated Microwave Pulses and High-Spin Ions at Zero Magnetic Fields": [
        "Russia"
    ]
}